rllib_emecom/__init__.py
rllib_emecom/env/__init__.py
rllib_emecom/env/goal_comms_gridworld.py
rllib_emecom/macrl/__init__.py
rllib_emecom/macrl/macrl_action_head.py
rllib_emecom/macrl/macrl_agent.py
rllib_emecom/macrl/macrl_config.py
rllib_emecom/macrl/macrl_module_spec.py
rllib_emecom/macrl/comms/__init__.py
rllib_emecom/macrl/comms/comm_channel_fn.py
rllib_emecom/macrl/comms/comms_spec.py
rllib_emecom/macrl/comms/dru.py
rllib_emecom/macrl/comms/gumbel_softmax.py
rllib_emecom/macrl/comms/straight_through.py
rllib_emecom/macrl/dqn/__init__.py
rllib_emecom/macrl/ppo/__init__.py
rllib_emecom/macrl/ppo/macrl_ppo.py
rllib_emecom/macrl/ppo/macrl_ppo_learner.py
rllib_emecom/macrl/ppo/macrl_ppo_module.py
rllib_emecom/tests/__init__.py
rllib_emecom/tests/test_macrl_module.py
rllib_emecom/tests/test_train.py
rllib_emecom/tests/utils.py
rllib_emecom/train/__init__.py
rllib_emecom/train/configs.py
rllib_emecom/train/goal_comms.py
rllib_emecom/utils/__init__.py
rllib_emecom/utils/comms_data_collection.py
rllib_emecom/utils/comms_renderer.py
rllib_emecom/utils/draw_macrl_graphs.py
rllib_emecom/utils/experiment_utils.py
rllib_emecom/utils/general.py
rllib_emecom/utils/plot_gradients.py
rllib_emecom/utils/register_envs.py
rllib_emecom/utils/video_callback.py
rllib_emecom/utils/video_utils.py
rllib_emecom-0.0.7.dist-info/LICENSE
rllib_emecom-0.0.7.dist-info/METADATA
rllib_emecom-0.0.7.dist-info/WHEEL
rllib_emecom-0.0.7.dist-info/top_level.txt
rllib_emecom-0.0.7.dist-info/RECORD
