Metadata-Version: 2.1
Name: rllib-emecom
Version: 0.0.7
Summary: Framework for Emergent Communication using RLlib
Home-page: https://github.com/DylanCope/rllib_emecom
Author: Dylan R. Cope
License-File: LICENSE
Requires-Dist: ray[rllib] >=2.7.0rc0
Requires-Dist: torch >=2.1.0
Requires-Dist: gymnasium >=0.28.1
Requires-Dist: pettingzoo >=1.24.1
Requires-Dist: numpy >=1.23.5
Requires-Dist: pandas >=1.3.5
Requires-Dist: networkx >=2.8.8
Requires-Dist: matplotlib >=3.6.2
Requires-Dist: imageio[ffmpeg] >=2.31.3
Requires-Dist: seaborn >=0.11.2
Requires-Dist: torchviz >=0.0.2
Requires-Dist: torchview >=0.2.6
